{
  "prepare_queue": {
    "installed": [],
    "uninstalled": []
  },
  "config_munge": {
    "files": {}
  },
  "installed_plugins": {
    "cordova-plugin-camera": {
      "PACKAGE_NAME": "reporteapp.ionic.starter"
    },
    "cordova-plugin-device": {
      "PACKAGE_NAME": "reporteapp.ionic.starter"
    },
    "cordova-plugin-ionic-webview": {
      "PACKAGE_NAME": "reporteapp.ionic.starter"
    },
    "cordova-plugin-splashscreen": {
      "PACKAGE_NAME": "reporteapp.ionic.starter"
    },
    "cordova-plugin-whitelist": {
      "PACKAGE_NAME": "reporteapp.ionic.starter"
    },
    "cordova-sqlite-storage": {
      "PACKAGE_NAME": "reporteapp.ionic.starter"
    },
    "ionic-plugin-keyboard": {
      "PACKAGE_NAME": "reporteapp.ionic.starter"
    }
  },
  "dependent_plugins": {}
}